{
  "sections": {
    "main": {
      "type": "main-page",
      "disabled": true,
      "settings": {
        "padding_top": 28,
        "padding_bottom": 28
      }
    },
    "1654068533ed7bd583": {
      "type": "dc-about-hero",
      "settings": {
        "hero_img": "shopify:\/\/shop_images\/Image_2x_39e61b2e-7305-4cd7-8686-8ddaa5d55b19.png",
        "hero_align": "center",
        "hero_title": "About delcon",
        "hero_subtitle": "Elke hond en elke kat heeft eigen specifieke behoeften. Daarom maken wij met veel zorg voeding die aangepast is aan jouw pluizige vriend."
      }
    },
    "165408112156807147": {
      "type": "dc-features-section",
      "blocks": {
        "eb2ee39f-0126-44c5-b101-3d48956f4777": {
          "type": "features",
          "settings": {
            "logo_img": "shopify:\/\/shop_images\/Icon_2x_4dcbb3d9-27ad-4898-afe7-a3fb25e3168b.png",
            "logo_title": "BELGISCH",
            "logo_desc": "Lorem ipsum dolor sit amet, consetetur sadipscing elitr, sed diam nonumy eirmod tempor invidunt ut labore et"
          }
        },
        "4b905781-1823-4975-a835-3b61d4f8515b": {
          "type": "features",
          "settings": {
            "logo_img": "shopify:\/\/shop_images\/Icon_2x_3dcc2c82-5820-4af0-870a-1fdc3848120f.png",
            "logo_title": "SNELLE VERZENDING",
            "logo_desc": "Lorem ipsum dolor sit amet, consetetur sadipscing elitr, sed diam nonumy eirmod tempor invidunt ut labore et"
          }
        },
        "7e4364a3-ae32-426a-9073-22c5090ba52c": {
          "type": "features",
          "settings": {
            "logo_img": "shopify:\/\/shop_images\/Icon_2x_7445ba4d-c2b8-4b72-80ae-44e592cccc0a.png",
            "logo_title": "KWALITEIT",
            "logo_desc": "Lorem ipsum dolor sit amet, consetetur sadipscing elitr, sed diam nonumy eirmod tempor invidunt ut labore et"
          }
        },
        "ee9efaa3-304f-4611-a2b8-056859d177ab": {
          "type": "features",
          "settings": {
            "logo_img": "shopify:\/\/shop_images\/Icon_2x_d069f4b3-d157-48b1-b4dc-4e2439b9fc30.png",
            "logo_title": "CUSTOMER SERVICE",
            "logo_desc": "Lorem ipsum dolor sit amet, consetetur sadipscing elitr, sed diam nonumy eirmod tempor invidunt ut labore et"
          }
        }
      },
      "block_order": [
        "eb2ee39f-0126-44c5-b101-3d48956f4777",
        "4b905781-1823-4975-a835-3b61d4f8515b",
        "7e4364a3-ae32-426a-9073-22c5090ba52c",
        "ee9efaa3-304f-4611-a2b8-056859d177ab"
      ],
      "settings": {
        "feature_background": "#e4edf2"
      }
    },
    "165408112696adb82f": {
      "type": "dc-img-video-text",
      "settings": {
        "background_color": "#bdb4ac",
        "media_alignment": "left",
        "section_type": "img_txt",
        "section_image": "shopify:\/\/shop_images\/Image_2x_08842411-8838-4190-9f06-a6f9ef370da4.png",
        "product_video": "",
        "video_link": "",
        "custom_logo": "",
        "section_subtitle": "MEER DAN X JAAR ERVARING",
        "section_title": "Onze geschiedenis",
        "section_text": "<p>Lorem ipsum dolor sit amet, consetetur sadipscing elitr, sed diam nonumy eirmod tempor invidunt ut labore et dolore magna aliquyam erat, sed diam voluptua. At vero eos et accusam et justo duo dolores et ea rebum. Stet clita kasd gubergren, no sea<\/p><p>Lorem ipsum dolor sit amet, consetetur sadipscing elitr, sed diam nonumy eirmod tempor invidunt ut labore et dolore magna aliquyam erat, sed diam voluptua. At vero eos et accusam et justo duo dolores et ea rebum. Stet clita kasd gubergren, no sea<\/p>",
        "section_link": "",
        "section_url": "",
        "isProductFinder": false,
        "isProefpakketten": false,
        "proefpakketten_text": "",
        "section_btn_text": "",
        "section_btn_url": ""
      }
    },
    "1654081203ec6b513b": {
      "type": "dc-img-video-text",
      "settings": {
        "background_color": "#f2f1f0",
        "media_alignment": "right",
        "section_type": "img_txt",
        "section_image": "shopify:\/\/shop_images\/Image_2x_08842411-8838-4190-9f06-a6f9ef370da4.png",
        "product_video": "",
        "video_link": "",
        "custom_logo": "",
        "section_subtitle": "BELGISCH",
        "section_title": "Met onze korte keten gaan we voor duurzaamheid",
        "section_text": "<p>Lorem ipsum dolor sit amet, consetetur sadipscing elitr, sed diam nonumy eirmod tempor invidunt ut labore et dolore magna aliquyam erat, sed diam voluptua. At vero eos et accusam et justo duo dolores et ea rebum. Stet clita kasd gubergren, no sea<\/p>",
        "section_link": "",
        "section_url": "",
        "isProductFinder": false,
        "isProefpakketten": false,
        "proefpakketten_text": "",
        "section_btn_text": "",
        "section_btn_url": ""
      }
    },
    "165408120865a70365": {
      "type": "dc-img-video-text",
      "settings": {
        "background_color": "#bdb4ac",
        "media_alignment": "left",
        "section_type": "img_txt",
        "section_image": "shopify:\/\/shop_images\/Image_2x_08842411-8838-4190-9f06-a6f9ef370da4.png",
        "product_video": "",
        "video_link": "",
        "custom_logo": "",
        "section_subtitle": "KWALITEIT",
        "section_title": "We streven ernaar een icoon te zijn van ware kwaliteit.",
        "section_text": "<p>Onze voeding is met veel zorg geformuleerd. Ze is enkel opgebouwd uit de meest <strong>verfijnde ingrediënten<\/strong>. Zo bekomen wij de meest gezonde voeding waarop jij trots mag zijn dat je ze aan je geliefde viervoeter kan geven.<\/p>",
        "section_link": "",
        "section_url": "",
        "isProductFinder": false,
        "isProefpakketten": false,
        "proefpakketten_text": "",
        "section_btn_text": "",
        "section_btn_url": ""
      }
    },
    "165375100706003da3": {
      "type": "dc-all-ingredients",
      "blocks": {
        "8a234d5d-df38-463e-8fc9-868adab126b4": {
          "type": "select",
          "settings": {
            "ingredient_name": "Lamsvlees",
            "ingredient_details": "<p>Lorem ipsum dolor sit amet, consetetur sadipscing elitr, sed diam nonumy eirmod tempor invidunt ut labore et dolore magna aliquyam erat, sed diam<\/p><ul>\n<li><strong>Hoog in eiwitten<\/strong><\/li>\n<li>Voorziet in alle nodige aminozuren<\/li>\n<li>Vitamines B6, B2, B12<\/li>\n<\/ul>",
            "ingredient_image": "shopify:\/\/shop_images\/Image_2x_666f3257-609b-42ca-9017-3c089f2f3196.png"
          }
        },
        "094b3c94-995b-4601-b63f-a331308445f7": {
          "type": "select",
          "settings": {
            "ingredient_name": "Kippenvlees",
            "ingredient_details": "<p>Lorem ipsum dolor sit amet, consetetur sadipscing elitr, sed diam nonumy eirmod tempor invidunt ut labore et dolore magna aliquyam erat, sed diam<\/p><ul>\n<li><strong>Hoog in eiwitten<\/strong><\/li>\n<li>Voorziet in alle nodige aminozuren<\/li>\n<li>Vitamines B6, B2, B12<\/li>\n<\/ul>",
            "ingredient_image": "shopify:\/\/shop_images\/Image_2x_e91738de-bcc2-4a55-b173-43507937fd81.png"
          }
        },
        "ded2823c-274b-4fa9-94fc-69bbd51eb5d2": {
          "type": "select",
          "settings": {
            "ingredient_name": "Rijst",
            "ingredient_details": "<p>Lorem ipsum dolor sit amet, consetetur sadipscing elitr, sed diam nonumy eirmod tempor invidunt ut labore et dolore magna aliquyam erat, sed diam<\/p><ul>\n<li><strong>Hoog in eiwitten<\/strong><\/li>\n<li>Voorziet in alle nodige aminozuren<\/li>\n<li>Vitamines B6, B2, B12<\/li>\n<\/ul>",
            "ingredient_image": "shopify:\/\/shop_images\/Image_2x_7c6d9fee-f8e7-4d8f-9a84-02ed7613247c.png"
          }
        },
        "00752563-199a-4930-8eaa-f1b657c3cd82": {
          "type": "select",
          "settings": {
            "ingredient_name": "Lijnzaad",
            "ingredient_details": "<p>Lorem ipsum dolor sit amet, consetetur sadipscing elitr, sed diam nonumy eirmod tempor invidunt ut labore et dolore magna aliquyam erat, sed diam<\/p><ul>\n<li><strong>Hoog in eiwitten<\/strong><\/li>\n<li>Voorziet in alle nodige aminozuren<\/li>\n<li>Vitamines B6, B2, B12<\/li>\n<\/ul>",
            "ingredient_image": "shopify:\/\/shop_images\/Image_2x_08842411-8838-4190-9f06-a6f9ef370da4.png"
          }
        },
        "d87c8afd-9eb6-404a-b646-1f7f9fa4198f": {
          "type": "select",
          "settings": {
            "ingredient_name": "Bietenpulp",
            "ingredient_details": "<p>Lorem ipsum dolor sit amet, consetetur sadipscing elitr, sed diam nonumy eirmod tempor invidunt ut labore et dolore magna aliquyam erat, sed diam<\/p><ul>\n<li><strong>Hoog in eiwitten<\/strong><\/li>\n<li>Voorziet in alle nodige aminozuren<\/li>\n<li>Vitamines B6, B2, B12<\/li>\n<\/ul>",
            "ingredient_image": "shopify:\/\/shop_images\/Ontwerp_zonder_titel_31.png"
          }
        },
        "488b9acd-a59e-46bb-a840-41f17c015796": {
          "type": "select",
          "settings": {
            "ingredient_name": "Zalm",
            "ingredient_details": "<p>Lorem ipsum dolor sit amet, consetetur sadipscing elitr, sed diam nonumy eirmod tempor invidunt ut labore et dolore magna aliquyam erat, sed diam<\/p><ul>\n<li><strong>Hoog in eiwitten<\/strong><\/li>\n<li>Voorziet in alle nodige aminozuren<\/li>\n<li>Vitamines B6, B2, B12<\/li>\n<\/ul>",
            "ingredient_image": "shopify:\/\/shop_images\/Schermafbeelding_2022-04-26_om_15.52.49.png"
          }
        }
      },
      "block_order": [
        "8a234d5d-df38-463e-8fc9-868adab126b4",
        "094b3c94-995b-4601-b63f-a331308445f7",
        "ded2823c-274b-4fa9-94fc-69bbd51eb5d2",
        "00752563-199a-4930-8eaa-f1b657c3cd82",
        "d87c8afd-9eb6-404a-b646-1f7f9fa4198f",
        "488b9acd-a59e-46bb-a840-41f17c015796"
      ],
      "settings": {
        "ingredient_details_background": "#f2f1f0",
        "ingredient_title_background": "#bdb4ac",
        "media_alignment": "right",
        "section_subtitle": "INGREDIENTEN",
        "section_title": "Natuurlijke ingrediënten"
      }
    },
    "16540856797d06a4d2": {
      "type": "dc-our-team",
      "settings": {
        "section_background": "#f2f1f0",
        "section_image": "shopify:\/\/shop_images\/278830274_655325648864437_4669716093247795382_n_2x_41ce9113-3c03-4cbe-bb44-0c51c029beb7.png",
        "section_title": "Our Team",
        "section_text": "Lorem ipsum dolor sit amet, consetetur sadipscing elitr, sed diam nonumy eirmod tempor invidunt ut labore et dolore magna aliquyam erat, sed diam voluptua. At vero eos et accusam et justo duo dolores et ea rebum. Stet clita kasd gubergren, no sea takimata sanctus est."
      }
    },
    "1654081225eb27023c": {
      "type": "dc-newsletter",
      "settings": {
        "title": "Krijg nu 20% korting",
        "desc": "Schrijf je in op onze nieuwsbrief en blijf op de hoogte van acties en promoties. 20% korting die je kan gebruiken bij je volgende aankoop in onze shop",
        "email_placeholder": "Email adres",
        "subscribe_btn": "Send"
      }
    }
  },
  "order": [
    "main",
    "1654068533ed7bd583",
    "165408112156807147",
    "165408112696adb82f",
    "1654081203ec6b513b",
    "165408120865a70365",
    "165375100706003da3",
    "16540856797d06a4d2",
    "1654081225eb27023c"
  ]
}
